distronode/__init__.py
distronode/__main__.py
distronode/constants.py
distronode/context.py
distronode/keyword_desc.yml
distronode/release.py
distronode/_vendor/__init__.py
distronode/cli/__init__.py
distronode/cli/adhoc.py
distronode/cli/config.py
distronode/cli/console.py
distronode/cli/doc.py
distronode/cli/galaxy.py
distronode/cli/inventory.py
distronode/cli/playbook.py
distronode/cli/pull.py
distronode/cli/vault.py
distronode/cli/arguments/__init__.py
distronode/cli/arguments/option_helpers.py
distronode/cli/scripts/__init__.py
distronode/cli/scripts/distronode_connection_cli_stub.py
distronode/collections/__init__.py
distronode/collections/list.py
distronode/compat/__init__.py
distronode/compat/importlib_resources.py
distronode/compat/selectors/__init__.py
distronode/config/__init__.py
distronode/config/base.yml
distronode/config/distronode_builtin_runtime.yml
distronode/config/manager.py
distronode/errors/__init__.py
distronode/errors/yaml_strings.py
distronode/executor/__init__.py
distronode/executor/action_write_locks.py
distronode/executor/interpreter_discovery.py
distronode/executor/module_common.py
distronode/executor/play_iterator.py
distronode/executor/playbook_executor.py
distronode/executor/stats.py
distronode/executor/task_executor.py
distronode/executor/task_queue_manager.py
distronode/executor/task_result.py
distronode/executor/discovery/__init__.py
distronode/executor/discovery/python_target.py
distronode/executor/powershell/__init__.py
distronode/executor/powershell/async_watchdog.ps1
distronode/executor/powershell/async_wrapper.ps1
distronode/executor/powershell/become_wrapper.ps1
distronode/executor/powershell/bootstrap_wrapper.ps1
distronode/executor/powershell/coverage_wrapper.ps1
distronode/executor/powershell/exec_wrapper.ps1
distronode/executor/powershell/module_manifest.py
distronode/executor/powershell/module_powershell_wrapper.ps1
distronode/executor/powershell/module_script_wrapper.ps1
distronode_core-2.16.1.dist-info/COPYING
distronode_core-2.16.1.dist-info/METADATA
distronode_core-2.16.1.dist-info/WHEEL
distronode_core-2.16.1.dist-info/entry_points.txt
distronode_core-2.16.1.dist-info/top_level.txt
distronode_core-2.16.1.dist-info/RECORD
