Metadata-Version: 2.1
Name: distronode-core
Version: 2.16.1
Summary: Radically simple IT automation
Home-page: https://distronode.khulnasoft.com/
Author: Distronode, Inc.
Author-email: info@khulnasoft.com
License: GPLv3+
Project-URL: Bug Tracker, https://github.com/distronode/distronode/issues
Project-URL: CI: Azure Pipelines, https://dev.azure.com/distronode/distronode/
Project-URL: Code of Conduct, https://distronode.khulnasoft.com/docs/distronode/latest/community/code_of_conduct.html
Project-URL: Documentation, https://distronode.khulnasoft.com/docs/distronode-core/
Project-URL: Mailing lists, https://distronode.khulnasoft.com/docs/distronode/latest/community/communication.html#mailing-list-information
Project-URL: Source Code, https://github.com/distronode/distronode
Classifier: Development Status :: 5 - Production/Stable
Classifier: Environment :: Console
Classifier: Intended Audience :: Developers
Classifier: Intended Audience :: Information Technology
Classifier: Intended Audience :: System Administrators
Classifier: License :: OSI Approved :: GNU General Public License v3 or later (GPLv3+)
Classifier: Natural Language :: English
Classifier: Operating System :: POSIX
Classifier: Programming Language :: Python :: 3
Classifier: Programming Language :: Python :: 3.10
Classifier: Programming Language :: Python :: 3.11
Classifier: Programming Language :: Python :: 3 :: Only
Classifier: Topic :: System :: Installation/Setup
Classifier: Topic :: System :: Systems Administration
Classifier: Topic :: Utilities
Requires-Python: >=3.10
License-File: COPYING
Requires-Dist: jinja2 >=3.0.0
Requires-Dist: PyYAML >=5.1
Requires-Dist: cryptography
Requires-Dist: packaging
Requires-Dist: resolvelib <1.1.0,>=0.5.3
